NBCS/NBCS.py
NBCS/__init__.py
NBCS-1.4.dist-info/LICENSE
NBCS-1.4.dist-info/METADATA
NBCS-1.4.dist-info/WHEEL
NBCS-1.4.dist-info/top_level.txt
NBCS-1.4.dist-info/RECORD
