Metadata-Version: 2.1
Name: NBCS
Version: 1.4
Summary: Python package that implements an adaptive classification and regression system using simplicial complexes. The package provides a novel approach to handling both binary and multi-class classification problems, as well as regression tasks, by adaptively creating a simplicial decomposition of the feature space.
Author: Amit Ronen
Author-email: erankfmn@gmail.com
Classifier: Programming Language :: Python :: 3
Classifier: License :: OSI Approved :: MIT License
Classifier: Operating System :: OS Independent
Requires-Python: >=3.6
License-File: LICENSE
Requires-Dist: numpy
Requires-Dist: scipy
Requires-Dist: scikit-learn
